maxtorch/__init__.py
maxtorch/utils.py
maxtorch/attention/__init__.py
maxtorch/attention/blocks.py
maxtorch/generative/__init__.py
maxtorch/generative/blocks.py
maxtorch/sequence/__init__.py
maxtorch/sequence/blocks.py
maxtorch/vision/__init__.py
maxtorch/vision/blocks.py
maxtorch/vision/models.py
maxtorch-0.1.0.dist-info/LICENSE
maxtorch-0.1.0.dist-info/METADATA
maxtorch-0.1.0.dist-info/WHEEL
maxtorch-0.1.0.dist-info/top_level.txt
maxtorch-0.1.0.dist-info/RECORD
